README.md
setup.py
lbrlabs_pulumi_launchdarkly/__init__.py
lbrlabs_pulumi_launchdarkly/_inputs.py
lbrlabs_pulumi_launchdarkly/_utilities.py
lbrlabs_pulumi_launchdarkly/access_token.py
lbrlabs_pulumi_launchdarkly/audit_log_subscription.py
lbrlabs_pulumi_launchdarkly/custom_role.py
lbrlabs_pulumi_launchdarkly/destination.py
lbrlabs_pulumi_launchdarkly/environment.py
lbrlabs_pulumi_launchdarkly/feature_flag.py
lbrlabs_pulumi_launchdarkly/feature_flag_environment.py
lbrlabs_pulumi_launchdarkly/flag_trigger.py
lbrlabs_pulumi_launchdarkly/get_audit_log_subscription.py
lbrlabs_pulumi_launchdarkly/get_environment.py
lbrlabs_pulumi_launchdarkly/get_feature_flag.py
lbrlabs_pulumi_launchdarkly/get_feature_flag_environment.py
lbrlabs_pulumi_launchdarkly/get_flag_trigger.py
lbrlabs_pulumi_launchdarkly/get_metric.py
lbrlabs_pulumi_launchdarkly/get_project.py
lbrlabs_pulumi_launchdarkly/get_relay_proxy_configuration.py
lbrlabs_pulumi_launchdarkly/get_segment.py
lbrlabs_pulumi_launchdarkly/get_team.py
lbrlabs_pulumi_launchdarkly/get_team_member.py
lbrlabs_pulumi_launchdarkly/get_team_members.py
lbrlabs_pulumi_launchdarkly/get_webhook.py
lbrlabs_pulumi_launchdarkly/metric.py
lbrlabs_pulumi_launchdarkly/outputs.py
lbrlabs_pulumi_launchdarkly/project.py
lbrlabs_pulumi_launchdarkly/provider.py
lbrlabs_pulumi_launchdarkly/pulumi-plugin.json
lbrlabs_pulumi_launchdarkly/py.typed
lbrlabs_pulumi_launchdarkly/relay_proxy_configuration.py
lbrlabs_pulumi_launchdarkly/segment.py
lbrlabs_pulumi_launchdarkly/team.py
lbrlabs_pulumi_launchdarkly/team_member.py
lbrlabs_pulumi_launchdarkly/webhook.py
lbrlabs_pulumi_launchdarkly.egg-info/PKG-INFO
lbrlabs_pulumi_launchdarkly.egg-info/SOURCES.txt
lbrlabs_pulumi_launchdarkly.egg-info/dependency_links.txt
lbrlabs_pulumi_launchdarkly.egg-info/not-zip-safe
lbrlabs_pulumi_launchdarkly.egg-info/requires.txt
lbrlabs_pulumi_launchdarkly.egg-info/top_level.txt
lbrlabs_pulumi_launchdarkly/config/__init__.py
lbrlabs_pulumi_launchdarkly/config/vars.py