Metadata-Version: 2.1
Name: lbrlabs-pulumi-launchdarkly
Version: 0.0.5
Summary: A Pulumi package for creating and managing launch darkly cloud resources.
Home-page: https://www.pulumi.com
License: UNKNOWN
Project-URL: Repository, https://github.com/lbrlabs/pulumi-launchdarkly
Keywords: pulumi launchdarkly lbrlabs
Platform: UNKNOWN
